jiosaavn/Async.py
jiosaavn/Sync.py
jiosaavn/__asyncJioSaavn.py
jiosaavn/__asyncparse.py
jiosaavn/__asyncrequests.py
jiosaavn/__baseApiUrl.py
jiosaavn/__constants.py
jiosaavn/__exceptions.py
jiosaavn/__helper.py
jiosaavn/__init__.py
jiosaavn/__syncJioSaavn.py
jiosaavn/__syncparse.py
jiosaavn/__syncrequests.py
jiosaavn/__useragent.py
jiosaavn/__validation.py
jiosaavn/_asyncFetch.py
jiosaavn/_commonparse.py
jiosaavn/_syncFetch.py
jiosaavn-0.1.0.dist-info/LICENSE.txt
jiosaavn-0.1.0.dist-info/METADATA
jiosaavn-0.1.0.dist-info/WHEEL
jiosaavn-0.1.0.dist-info/top_level.txt
jiosaavn-0.1.0.dist-info/RECORD
