Metadata-Version: 2.1
Name: jiosaavn
Version: 0.1.0
Summary: Search for JioSaavn songs & album. Get song ,album, lyric & playlist information from url or id.
Home-page: https://github.com/vidyasagar1432/jiosaavn
Author: vidya sagar
Author-email: svidya051@gmail.com
License: MIT
Keywords: jiosaavn,jio-saavn-api,jio-saavn,playlist,aiohttp,songs,albums,lyrics
Platform: UNKNOWN
Classifier: Development Status :: 4 - Beta
Classifier: Intended Audience :: Developers
Classifier: License :: OSI Approved :: MIT License
Classifier: Operating System :: OS Independent
Classifier: Programming Language :: Python :: 3
Requires-Python: >=3.6
